{"id":-126092,"path":"Clerk_默认","assetBundleId":-1,"components":[{"type":1,"id":-126094,"data":[-2.69000005722046,-0.899999976158142,-4.76999950408936,1,1,1,0.707106828689575,0,0,0.707106828689575]},{"type":2,"id":-126096,"enabled":1,"class":30,"data":[[[[[31,55526,"UnityEngine.GameObject, UnityEngine","SetActive",6,[null,null,"UnityEngine.Object, UnityEngine",0,0,"",1],2]]]],20,2,0,[[[]]],0,19,-126118,[19,-126154,19,-126162,19,-126170,19,-126178],19,-126186,19,-126194,19,-126202]},{"type":6,"id":-126098,"data":[0,0,0,1.5,1.5,1.5,1,1,null,null]}],"children":[{"id":-126100,"path":"Clerk_默认","assetBundleId":-1,"components":[{"type":15,"id":-126102,"data":[0.5,0.5,0,0,0,0,500,500,0,0,0,0,0,0,1,0.00499999988824129,0.00499999988824129,0.00499999988824129]},{"type":32,"id":-126104,"data":[100,100,0,2,0,"Default",0,1,33,55392,0,0,0,0,1]},{"type":20,"id":-126106,"enabled":1,"class":34,"data":[0,100,1,800,600,0,0,3,96,96,1,1]},{"type":20,"id":-126108,"enabled":1,"class":35,"data":[1,0,-1]},{"type":17,"id":-126110,"data":[1,1,1,0,1]}],"children":[{"id":-126112,"path":"Clerk_默认","assetBundleId":-1,"components":[{"type":15,"id":-126114,"data":[0.5,0.5,0.5,0.5,0.5,0.5,500,500,0,0,0,0,0,0,1,1,1,1]},{"type":16,"id":-126116,"data":[1]},{"type":20,"id":-126118,"enabled":1,"class":19,"data":[9,604,3,0,1,1,0,1,0,0,1,null,null,1,0,1,0.0710775852203369,1,1,0,0,0,0]}],"children":[],"data":["fill",0,1,0,5]},{"id":-126120,"path":"Clerk_默认","assetBundleId":-1,"components":[{"type":15,"id":-126122,"data":[0.5,0.5,0.5,0.5,0.5,0.5,300,300,0,0,0,0,0,0,1,1,1,1]},{"type":16,"id":-126124,"data":[1]},{"type":20,"id":-126126,"enabled":1,"class":19,"data":[9,604,0,0,1,4,1,1,0,0,1,null,null,1,0.867924511432648,0.478996068239212,0.478996068239212,1,1,0,0,0,0]}],"children":[],"data":["icon",0,1,0,5]},{"id":-126128,"path":"Clerk_默认","assetBundleId":-1,"components":[{"type":15,"id":-126130,"data":[0.5,0.5,0,0,0,0,100,100,94,50,0,0,0,0,1,1,1,1]},{"type":16,"id":-126132,"data":[1]},{"type":20,"id":-126134,"enabled":1,"class":19,"data":[9,612,0,0,1,4,1,1,0,0,1,null,null,1,1,0.933333396911621,0,1,1,0,0,0,0]}],"children":[],"data":["moneyIcon",0,1,0,5]},{"id":-126136,"path":"Clerk_默认","assetBundleId":-1,"components":[{"type":15,"id":-126138,"data":[0.5,0.5,1,0,1,0,320,80,-199,50,0,0,0,0,1,1,1,1]},{"type":16,"id":-126140,"data":[1]},{"type":20,"id":-126142,"enabled":1,"class":19,"data":[null,null,0,0,1,4,1,1,0,0,1,null,null,1,1,1,1,1,1,0,0,0,0]},{"type":20,"id":-126144,"enabled":1,"class":36,"data":[0,1,1,0,0,0,0,0,0,0,0,0,4]},{"type":20,"id":-126146,"enabled":1,"class":37,"data":[2,0]}],"children":[{"id":-126148,"path":"Clerk_默认","assetBundleId":-1,"components":[{"type":15,"id":-126150,"data":[0.5,0.5,0,1,0,1,80,80,40,-40,0,0,0,0,1,1,1,1]},{"type":16,"id":-126152,"data":[1]},{"type":20,"id":-126154,"enabled":1,"class":19,"data":[null,null,0,0,1,4,1,1,0,0,1,null,null,1,0.584905624389648,0.584905624389648,0.584905624389648,1,1,0,0,0,0]}],"children":[],"data":["Image",0,1,0,5]},{"id":-126156,"path":"Clerk_默认","assetBundleId":-1,"components":[{"type":15,"id":-126158,"data":[0.5,0.5,0,1,0,1,80,80,120,-40,0,0,0,0,1,1,1,1]},{"type":16,"id":-126160,"data":[1]},{"type":20,"id":-126162,"enabled":1,"class":19,"data":[null,null,0,0,1,4,1,1,0,0,1,null,null,1,0.584905624389648,0.584905624389648,0.584905624389648,1,1,0,0,0,0]}],"children":[],"data":["Image (1)",0,1,0,5]},{"id":-126164,"path":"Clerk_默认","assetBundleId":-1,"components":[{"type":15,"id":-126166,"data":[0.5,0.5,0,1,0,1,80,80,200,-40,0,0,0,0,1,1,1,1]},{"type":16,"id":-126168,"data":[1]},{"type":20,"id":-126170,"enabled":1,"class":19,"data":[null,null,0,0,1,4,1,1,0,0,1,null,null,1,0.584905624389648,0.584905624389648,0.584905624389648,1,1,0,0,0,0]}],"children":[],"data":["Image (2)",0,1,0,5]},{"id":-126172,"path":"Clerk_默认","assetBundleId":-1,"components":[{"type":15,"id":-126174,"data":[0.5,0.5,0,1,0,1,80,80,280,-40,0,0,0,0,1,1,1,1]},{"type":16,"id":-126176,"data":[1]},{"type":20,"id":-126178,"enabled":1,"class":19,"data":[null,null,0,0,1,4,1,1,0,0,1,null,null,1,0.584905624389648,0.584905624389648,0.584905624389648,1,1,0,0,0,0]}],"children":[],"data":["Image (3)",0,1,0,5]}],"data":["Numbs",0,1,0,5]},{"id":-126180,"path":"Clerk_默认","assetBundleId":-1,"components":[{"type":15,"id":-126182,"data":[0.5,0.5,0.5,0.5,0.5,0.5,500,500,0,0,0,0,0,0,1,1,1,1]},{"type":16,"id":-126184,"data":[1]},{"type":20,"id":-126186,"enabled":1,"class":19,"data":[9,604,0,0,1,4,1,1,0,0,1,null,null,1,1,1,1,0.0862745121121407,1,0,0,0,0]}],"children":[],"data":["borderImageNomal",0,1,0,5]},{"id":-126188,"path":"Clerk_默认","assetBundleId":-1,"components":[{"type":15,"id":-126190,"data":[0.5,0.5,0.5,0.5,0.5,0.5,500,500,0,0,0,0,0,0,1,1,1,1]},{"type":16,"id":-126192,"data":[1]},{"type":20,"id":-126194,"enabled":1,"class":19,"data":[9,604,0,0,1,4,1,1,0,0,1,null,null,1,0.25943398475647,0.980084896087646,1,0.439215689897537,1,0,0,0,0]}],"children":[],"data":["borderImageHighlight",0,0,0,5]},{"id":-126196,"path":"Clerk_默认","assetBundleId":-1,"components":[{"type":15,"id":-126198,"data":[0.5,0.5,0.5,0.5,0.5,0.5,500,500,0,0,0,0,0,0,1,1,1,1]},{"type":16,"id":-126200,"data":[1]},{"type":20,"id":-126202,"enabled":1,"class":19,"data":[9,604,0,0,1,4,1,1,0,0,1,null,null,1,1,0,0,0.5686274766922,1,0,0,0,0]}],"children":[],"data":["borderImageNomoney",0,0,0,5]}],"data":["Canvas",0,1,0,5]}],"data":["Clerk_默认",0,1,0,0]}